noise.py
setup.py
noise.py.egg-info/PKG-INFO
noise.py.egg-info/SOURCES.txt
noise.py.egg-info/dependency_links.txt
noise.py.egg-info/top_level.txt