Metadata-Version: 1.0
Name: noise.py
Version: 0.0.4
Summary: Python client for github.com/eleme/noise
Home-page: https://github.com/eleme/noise/tree/master/clients/python
Author: hit9
Author-email: hit9@ele.me
License: MIT
Keywords: noise,client
Platform: UNKNOWN
